{
  "items": [
    {
      "name": 18,
      "group": "1",
      "avg": "4.25",
      "debt": null
    },
    {
      "name": "Sidorov Ivan",
      "group": 31,
      "avg": 4,
      "debt": "C++"
    },
    {
      "name": "Pertov Nikita",
      "group": "IU8-31",
      "avg": 3.3,
      "debt": [
        "C++",
        "Linux",
        "Network"
      ]
    },
    {
      "name": "Kirill Kirillov",
      "group": "IU2-11",
      "avg": 4.92,
      "debt": [
        "fizra",
        "Network"
      ]
    }
  ],
  "_meta": {
    "count": 4
  }
}